autonamed/__init__.py
autonamed/component.py
pulumi_autonamed-0.1.0.dist-info/METADATA
pulumi_autonamed-0.1.0.dist-info/WHEEL
pulumi_autonamed-0.1.0.dist-info/top_level.txt
pulumi_autonamed-0.1.0.dist-info/RECORD
